cacode_framework/__init__.py
cacode_framework/MainWork/CACodeAdapter.py
cacode_framework/MainWork/CACodeAopContainer.py
cacode_framework/MainWork/CACodeConfig.py
cacode_framework/MainWork/CACodePureORM.py
cacode_framework/MainWork/CACodeRepository.py
cacode_framework/MainWork/__init__.py
cacode_framework/anno/__init__.py
cacode_framework/anno/annos.py
cacode_framework/cacode/Factory.py
cacode_framework/cacode/Modes.py
cacode_framework/cacode/Serialize.py
cacode_framework/cacode/__init__.py
cacode_framework/cacode/ReviewJson/JSON.py
cacode_framework/cacode/ReviewJson/__init__.py
cacode_framework/cacode/ReviewJson/compat.py
cacode_framework/cacode/ReviewJson/decoder.py
cacode_framework/cacode/ReviewJson/encoder.py
cacode_framework/cacode/ReviewJson/errors.py
cacode_framework/cacode/ReviewJson/ordered_dict.py
cacode_framework/cacode/ReviewJson/raw_json.py
cacode_framework/cacode/ReviewJson/scanner.py
cacode_framework/cacode/ReviewJson/tool.py
cacode_framework/exception/__init__.py
cacode_framework/exception/e_fields.py
cacode_framework/field/FManage.py
cacode_framework/field/MySqlDefault.py
cacode_framework/field/__init__.py
cacode_framework/opera/CompulsoryRun.py
cacode_framework/opera/__init__.py
cacode_framework/opera/op_db.py
cacode_framework/pojoManager/Manage.py
cacode_framework/pojoManager/__init__.py
cacode_framework/pojoManager/tag.py
cacode_framework/util/DbUtil.py
cacode_framework/util/Log.py
cacode_framework/util/ParseUtil.py
cacode_framework/util/__init__.py
cacode_framework/util/DBPool/__init__.py
cacode_framework/util/DBPool/persistent_db.py
cacode_framework/util/DBPool/persistent_pg.py
cacode_framework/util/DBPool/pooled_db.py
cacode_framework/util/DBPool/pooled_pg.py
cacode_framework/util/DBPool/simple_pooled_db.py
cacode_framework/util/DBPool/simple_pooled_pg.py
cacode_framework/util/DBPool/steady_db.py
cacode_framework/util/DBPool/steady_pg.py
test/__init__.py
test/testFunc.py
test/modules/DatabaseConf.py
test/modules/MySqlTest.py
cacode_framework-1.0.0.dist-info/LICENSE
cacode_framework-1.0.0.dist-info/METADATA
cacode_framework-1.0.0.dist-info/WHEEL
cacode_framework-1.0.0.dist-info/top_level.txt
cacode_framework-1.0.0.dist-info/RECORD
